archivefile/__init__.py
archivefile/_adapters/_base.py
archivefile/_adapters/_rar.py
archivefile/_adapters/_sevenzip.py
archivefile/_adapters/_tar.py
archivefile/_adapters/_zip.py
archivefile/_core.py
archivefile/_enums.py
archivefile/_models.py
archivefile/_types.py
archivefile/_utils.py
archivefile/_version.py
archivefile/py.typed
archivefile-1.0.0.dist-info/METADATA
archivefile-1.0.0.dist-info/WHEEL
archivefile-1.0.0.dist-info/RECORD
