Metadata-Version: 2.1
Name: archivefile
Version: 1.0.0
Summary: Unified interface for tar, zip, sevenzip, and rar files
Home-page: https://archivefile.ravencentric.cc
License: Unlicense
Keywords: archive,archivefile,zipfile,tarfile,sevenzip,rarfile
Author: Ravencentric
Author-email: me@ravencentric.cc
Requires-Python: >=3.10
Classifier: License :: OSI Approved
Classifier: License :: OSI Approved :: The Unlicense (Unlicense)
Classifier: Operating System :: OS Independent
Classifier: Programming Language :: Python :: 3
Classifier: Programming Language :: Python :: 3.10
Classifier: Programming Language :: Python :: 3.11
Classifier: Programming Language :: Python :: 3.12
Classifier: Topic :: System :: Archiving
Classifier: Topic :: System :: Archiving :: Compression
Classifier: Typing :: Typed
Provides-Extra: all
Provides-Extra: bigtree
Provides-Extra: rich
Requires-Dist: bigtree (>=0.19.3) ; extra == "bigtree" or extra == "all"
Requires-Dist: py7zr (>=0.21.1)
Requires-Dist: pydantic (>=2.8.2)
Requires-Dist: rarfile (>=4.2)
Requires-Dist: rich (>=13.7.1) ; extra == "rich" or extra == "all"
Requires-Dist: typing-extensions (>=4.12.2)
Project-URL: Documentation, https://archivefile.ravencentric.cc
Project-URL: Repository, https://github.com/Ravencentric/archivefile
